{
    "web": {
        "client_id": "124600701920-qb1eh6dvqmndob54i11gcrps50io5agn.apps.googleusercontent.com",
        "project_id": "prime-amulet-327105",
        "auth_uri": "https://accounts.google.com/o/oauth2/auth",
        "token_uri": "https://oauth2.googleapis.com/token",
        "auth_provider_x509_cert_url": "https://www.googleapis.com/oauth2/v1/certs",
        "client_secret": "jEiMuPFg3DygGtEvC9bEVbp7",
        "redirect_uris": [
            "http://localhost:3000",
            "http://localhost:5000/auth/google/redirect",
            "https://developers.google.com/oauthplayground"
        ],
        "javascript_origins": ["http://localhost:5000"]
    }
}